mkdocs_puml/__init__.py
mkdocs_puml/config.py
mkdocs_puml/encoder.py
mkdocs_puml/model.py
mkdocs_puml/plugin.py
mkdocs_puml/puml.py
mkdocs_puml/static/interaction.css
mkdocs_puml/static/interaction.js
mkdocs_puml/static/puml.css
mkdocs_puml/static/puml.js
mkdocs_puml/storage.py
mkdocs_puml/theme.py
mkdocs_puml/utils.py
mkdocs_puml-2.2.0.dist-info/LICENSE
mkdocs_puml-2.2.0.dist-info/METADATA
mkdocs_puml-2.2.0.dist-info/WHEEL
mkdocs_puml-2.2.0.dist-info/entry_points.txt
mkdocs_puml-2.2.0.dist-info/RECORD
