Metadata-Version: 2.1
Name: mkdocs_puml
Version: 2.2.0
Summary: Package that brings PlantUML to MkDocs
Home-page: https://github.com/MikhailKravets/mkdocs_puml
License: MIT
Keywords: markdown,mkdocs,plantuml,puml,uml,documentation,diagram,uml-diagrams,plugin,mkdocs-plugin
Author: Mikhail Kravets
Author-email: michkravets@gmail.com
Requires-Python: >=3.9,<4.0
Classifier: Development Status :: 5 - Production/Stable
Classifier: Framework :: MkDocs
Classifier: Intended Audience :: Developers
Classifier: License :: OSI Approved :: MIT License
Classifier: Programming Language :: Python :: 3
Classifier: Programming Language :: Python :: 3.9
Classifier: Programming Language :: Python :: 3.10
Classifier: Programming Language :: Python :: 3.11
Classifier: Programming Language :: Python :: 3.12
Classifier: Programming Language :: Python :: 3.13
Classifier: Topic :: Documentation
Classifier: Topic :: Software Development :: Documentation
Classifier: Topic :: Text Processing :: Markup :: Markdown
Requires-Dist: httpx (>=0.27,<0.28)
Requires-Dist: markdown (>=3.2,<4.0)
Requires-Dist: mkdocs (>=1.4,<2.0)
Requires-Dist: msgpack (>=1.1,<2.0)
Requires-Dist: rich (>=13.9,<14.0)
Project-URL: Documentation, https://mikhailkravets.github.io/mkdocs_puml/
Project-URL: Repository, https://github.com/MikhailKravets/mkdocs_puml
